CHANGES.txt
MANIFEST.in
MIT-LICENSE.txt
README.txt
development.ini
production.ini
setup.cfg
setup.py
ewscal/__init__.py
ewscal/freebusy.py
ewscal.egg-info/PKG-INFO
ewscal.egg-info/SOURCES.txt
ewscal.egg-info/dependency_links.txt
ewscal.egg-info/entry_points.txt
ewscal.egg-info/not-zip-safe
ewscal.egg-info/requires.txt
ewscal.egg-info/top_level.txt
ewscal/static/calendar.js
ewscal/static/index.html
ewscal/static/js/d3.v2.min.js
ewscal/static/js/iso8601.js
ewscal/templates/index.pt