Metadata-Version: 1.1
Name: ewscal
Version: 0.0
Summary: Render Exchange calendars to SVG using d3.js
Home-page: UNKNOWN
Author: Daniel Holth
Author-email: dholth@fastmail.fm
License: MIT
Keywords: web pyramid pylons
Platform: UNKNOWN
Classifier: Programming Language :: Python
Classifier: Framework :: Pylons
Classifier: Topic :: Internet :: WWW/HTTP
Classifier: Topic :: Internet :: WWW/HTTP :: WSGI :: Application
